snakepython/__init__.py
snakepython-0.0.1.dist-info/METADATA
snakepython-0.0.1.dist-info/WHEEL
snakepython-0.0.1.dist-info/top_level.txt
snakepython-0.0.1.dist-info/RECORD
